odoo/addons/purchase_work_acceptance/README.rst
odoo/addons/purchase_work_acceptance/__init__.py
odoo/addons/purchase_work_acceptance/__manifest__.py
odoo/addons/purchase_work_acceptance/data/work_acceptance_sequence.xml
odoo/addons/purchase_work_acceptance/i18n/pt_BR.po
odoo/addons/purchase_work_acceptance/i18n/purchase_work_acceptance.pot
odoo/addons/purchase_work_acceptance/models/__init__.py
odoo/addons/purchase_work_acceptance/models/account_move.py
odoo/addons/purchase_work_acceptance/models/purchase.py
odoo/addons/purchase_work_acceptance/models/res_config_settings.py
odoo/addons/purchase_work_acceptance/models/stock_picking.py
odoo/addons/purchase_work_acceptance/models/work_acceptance.py
odoo/addons/purchase_work_acceptance/readme/CONFIGURE.rst
odoo/addons/purchase_work_acceptance/readme/CONTRIBUTORS.rst
odoo/addons/purchase_work_acceptance/readme/DESCRIPTION.rst
odoo/addons/purchase_work_acceptance/readme/USAGE.rst
odoo/addons/purchase_work_acceptance/security/ir.model.access.csv
odoo/addons/purchase_work_acceptance/security/security.xml
odoo/addons/purchase_work_acceptance/static/description/icon.png
odoo/addons/purchase_work_acceptance/static/description/index.html
odoo/addons/purchase_work_acceptance/tests/__init__.py
odoo/addons/purchase_work_acceptance/tests/test_purchase_work_acceptance.py
odoo/addons/purchase_work_acceptance/views/account_move_views.xml
odoo/addons/purchase_work_acceptance/views/purchase_views.xml
odoo/addons/purchase_work_acceptance/views/res_config_settings_views.xml
odoo/addons/purchase_work_acceptance/views/stock_picking_type_views.xml
odoo/addons/purchase_work_acceptance/views/stock_picking_views.xml
odoo/addons/purchase_work_acceptance/views/work_acceptance_views.xml
odoo/addons/purchase_work_acceptance/wizard/__init__.py
odoo/addons/purchase_work_acceptance/wizard/select_work_acceptance_wizard.py
odoo/addons/purchase_work_acceptance/wizard/select_work_acceptance_wizard_views.xml
odoo14_addon_purchase_work_acceptance-14.0.1.3.1.dist-info/METADATA
odoo14_addon_purchase_work_acceptance-14.0.1.3.1.dist-info/WHEEL
odoo14_addon_purchase_work_acceptance-14.0.1.3.1.dist-info/top_level.txt
odoo14_addon_purchase_work_acceptance-14.0.1.3.1.dist-info/RECORD
